modxlib23/__init__.py
modxlib23/modxlib23.py
modxlib23-0.2.1.dist-info/LICENSE
modxlib23-0.2.1.dist-info/METADATA
modxlib23-0.2.1.dist-info/WHEEL
modxlib23-0.2.1.dist-info/top_level.txt
modxlib23-0.2.1.dist-info/RECORD
